LICENSE
MANIFEST.in
setup.py
dbmessages/__init__.py
dbmessages/admin.py
dbmessages/middleware.py
dbmessages/models.py
django_dbmessages.egg-info/PKG-INFO
django_dbmessages.egg-info/SOURCES.txt
django_dbmessages.egg-info/dependency_links.txt
django_dbmessages.egg-info/top_level.txt