Metadata-Version: 1.1
Name: django-dbmessages
Version: 0.1.0
Summary: Request-independent messaging for Django on top of contrib.messages
Home-page: UNKNOWN
Author: Anton Strogonoff
Author-email: anton@strogonoff.name
License: BSD License
Download-URL: http://github.com/strogonoff/django-dbmessages
Platform: UNKNOWN
Classifier: Environment :: Web Environment
Classifier: Framework :: Django
Classifier: Intended Audience :: Developers
Classifier: License :: OSI Approved :: BSD License
Classifier: Operating System :: OS Independent
Classifier: Programming Language :: Python
Classifier: Programming Language :: Python :: 2
Classifier: Programming Language :: Python :: 2.7
Classifier: Topic :: Internet :: WWW/HTTP
Classifier: Topic :: Internet :: WWW/HTTP :: Dynamic Content
